email_validation_pkg/__init__.py
email_validation_pkg/email_validation.py
email_validation_pkg-0.0.2.dist-info/LICENSE
email_validation_pkg-0.0.2.dist-info/METADATA
email_validation_pkg-0.0.2.dist-info/WHEEL
email_validation_pkg-0.0.2.dist-info/top_level.txt
email_validation_pkg-0.0.2.dist-info/RECORD
