Metadata-Version: 2.1
Name: email-validation-pkg
Version: 0.0.2
Summary: Python Email Validation
Home-page: https://github.com/pypa/sampleproject
Author: Neasa Ni
Author-email: x20165935@student.ncirl.ie
License: UNKNOWN
Platform: UNKNOWN
Classifier: Programming Language :: Python :: 3
Classifier: License :: OSI Approved :: MIT License
Classifier: Operating System :: OS Independent
Requires-Python: >=3.6
